pyvespa-0.61.0.dist-info/licenses/LICENSE
vespa/__init__.py
vespa/application.py
vespa/deployment.py
vespa/evaluation.py
vespa/exceptions.py
vespa/io.py
vespa/package.py
vespa/py.typed
vespa/configuration/__init__.py
vespa/configuration/deployment.py
vespa/configuration/query_profiles.py
vespa/configuration/services.py
vespa/configuration/vt.py
vespa/configuration/relaxng/__init__.py
vespa/querybuilder/__init__.py
vespa/querybuilder/builder/__init__.py
vespa/querybuilder/builder/builder.py
vespa/querybuilder/grouping/__init__.py
vespa/querybuilder/grouping/grouping.py
vespa/resources/__init__.py
vespa/templates/deployment.xml
vespa/templates/hosts.xml
vespa/templates/macros.txt
vespa/templates/query_profile.xml
vespa/templates/query_profile_type.xml
vespa/templates/schema.txt
vespa/templates/services.xml
vespa/templates/validation-overrides.xml
vespa/utils/__init__.py
vespa/utils/deploy_prod.py
vespa/utils/notebook.py
vespa/utils/update_version.py
pyvespa-0.61.0.dist-info/METADATA
pyvespa-0.61.0.dist-info/WHEEL
pyvespa-0.61.0.dist-info/top_level.txt
pyvespa-0.61.0.dist-info/RECORD
