Metadata-Version: 2.4
Name: pyvespa
Version: 0.61.0
Summary: Python API for vespa.ai
Author: Thiago G. Martins, Thomas Thoresen
Maintainer-email: Thomas Thoresen <thomas@vespa.ai>
License:                               Apache License
Project-URL: homepage, https://pypi.org/project/pyvespa
Project-URL: repository, https://github.com/vespa-engine/pyvespa
Keywords: vespa,search engine,data science
Classifier: License :: OSI Approved :: Apache Software License
Requires-Python: >=3.9
License-File: LICENSE
Requires-Dist: requests
Requires-Dist: requests_toolbelt
Requires-Dist: docker
Requires-Dist: jinja2
Requires-Dist: cryptography
Requires-Dist: aiohttp
Requires-Dist: httpx[http2]
Requires-Dist: tenacity>=8.4.1
Requires-Dist: typing_extensions
Requires-Dist: python-dateutil
Requires-Dist: fastcore>=1.7.8
Requires-Dist: lxml
Provides-Extra: vespacli
Requires-Dist: vespacli; extra == "vespacli"
Provides-Extra: build
Requires-Dist: setuptools==69.0.3; extra == "build"
Requires-Dist: build==1.0.3; extra == "build"
Requires-Dist: twine==5.1.1; extra == "build"
Requires-Dist: toml==0.10.2; extra == "build"
Requires-Dist: ruff; extra == "build"
Provides-Extra: unittest
Requires-Dist: pytest; extra == "unittest"
Requires-Dist: requests-mock; extra == "unittest"
Requires-Dist: vespacli; extra == "unittest"
Requires-Dist: pytest-asyncio; extra == "unittest"
Requires-Dist: mypy>=1.14.1; extra == "unittest"
Provides-Extra: docs
Requires-Dist: ipykernel; extra == "docs"
Requires-Dist: nbconvert; extra == "docs"
Requires-Dist: jupyter; extra == "docs"
Requires-Dist: mkdocs-material; extra == "docs"
Requires-Dist: mkdocs-jupyter; extra == "docs"
Requires-Dist: mkdocstrings[python]; extra == "docs"
Requires-Dist: mkdocs-autoapi; extra == "docs"
Requires-Dist: mkdocs-linkcheck; extra == "docs"
Requires-Dist: mktestdocs; extra == "docs"
Requires-Dist: pytest; extra == "docs"
Provides-Extra: feed
Requires-Dist: PyYAML; extra == "feed"
Requires-Dist: spacy; extra == "feed"
Requires-Dist: mmh3; extra == "feed"
Requires-Dist: requests<=2.31.0; extra == "feed"
Requires-Dist: html5lib; extra == "feed"
Requires-Dist: beautifulsoup4; extra == "feed"
Requires-Dist: markdownify; extra == "feed"
Requires-Dist: tiktoken; extra == "feed"
Requires-Dist: vespacli; extra == "feed"
Provides-Extra: notebooks
Requires-Dist: notebook; extra == "notebooks"
Requires-Dist: nbconvert<=7.12.0; extra == "notebooks"
Requires-Dist: ipykernel; extra == "notebooks"
Requires-Dist: jupytext; extra == "notebooks"
Requires-Dist: numpy; extra == "notebooks"
Requires-Dist: pandas; extra == "notebooks"
Requires-Dist: plotly; extra == "notebooks"
Requires-Dist: torch; extra == "notebooks"
Requires-Dist: openai; extra == "notebooks"
Requires-Dist: datasets<4.0.0; extra == "notebooks"
Requires-Dist: ir_datasets; extra == "notebooks"
Requires-Dist: pytrec_eval; extra == "notebooks"
Requires-Dist: papermill; extra == "notebooks"
Requires-Dist: ipywidgets; extra == "notebooks"
Requires-Dist: matplotlib; extra == "notebooks"
Provides-Extra: dev
Requires-Dist: pre-commit; extra == "dev"
Requires-Dist: vespacli; extra == "dev"
Requires-Dist: datasets<4.0.0; extra == "dev"
Requires-Dist: pyvespa[unittest]; extra == "dev"
Requires-Dist: pyvespa[build]; extra == "dev"
Requires-Dist: ruff; extra == "dev"
Dynamic: license-file
